{"pageProps":{"post":{"id":11,"attributes":{"title":"A voz oculta da coruja tímida","content":"Era uma vez uma coruja chamada Aurora. Ela era uma coruja muito tímida e sempre se sentia insegura ao interagir com outros animais da floresta. Mas havia uma coisa que Aurora adorava fazer mais do que qualquer outra coisa: cantar.\n\nTodas as noites, Aurora cantava suavemente enquanto voava pela floresta. Ela amava a sensação de sua voz flutuando no ar noturno, mas sempre fazia isso quando sabia que não havia ninguém por perto para ouvir. Ela tinha medo de cantar em público e que os outros animais zombassem dela.\n\nUm dia, Aurora conheceu um filhote de coruja chamado Oliver. Oliver também amava cantar e ouvia Aurora cantando todas as noites. Ele admirava a voz de Aurora e queria aprender a cantar como ela. Aurora ficou surpresa e um pouco envergonhada que alguém tinha ouvido sua voz, mas ficou feliz em saber que alguém gostava da sua música.\n\nCom o tempo, Aurora começou a cantar para Oliver, e ele adorava ouvir sua voz. Ele a encorajou a cantar mais alto e mais forte. Aurora ainda estava um pouco tímida, mas começou a ganhar confiança com Oliver. Ela percebeu que seu medo de cantar em público era apenas um obstáculo que ela precisava superar.\n\nUm dia, Oliver perguntou a Aurora por que ela não cantava para outros animais da floresta. Aurora explicou que estava muito tímida e tinha medo do que os outros pensariam. Oliver sorriu e disse a Aurora que sua voz era linda e que ela deveria compartilhar sua música com o mundo.\n\nCom a ajuda de Oliver, Aurora finalmente encontrou a coragem de cantar em público. Ela se apresentou na árvore principal da floresta e cantou com toda a sua voz. Para sua surpresa, todos os animais pararam para ouvi-la e aplaudiram quando ela terminou. Aurora percebeu que sua música tinha o poder de trazer alegria para os outros, e ela nunca mais teve medo de cantar em público novamente.\n\nA partir daquele dia, Aurora se tornou uma das corujas mais conhecidas da floresta. As outras corujas vinham pedir conselhos a ela sobre como cantar e, às vezes, ela se juntava a outros animais para tocar música juntos. E assim, a coruja tímida encontrou sua voz e descobriu uma nova confiança dentro de si mesma.","slug":"post-8","createdAt":"2023-04-15T16:57:26.251Z","updatedAt":"2023-04-23T17:59:55.014Z","cover":{"data":{"id":15,"attributes":{"name":"fotos-corujas.jpg","alternativeText":null,"caption":null,"width":1200,"height":628,"formats":{"large":{"ext":".jpg","url":"https://res.cloudinary.com/duqhyfegq/image/upload/v1682272784/large_fotos_corujas_2ce24c5172.jpg","hash":"large_fotos_corujas_2ce24c5172","mime":"image/jpeg","name":"large_fotos-corujas.jpg","path":null,"size":95.64,"width":1000,"height":523,"provider_metadata":{"public_id":"large_fotos_corujas_2ce24c5172","resource_type":"image"}},"small":{"ext":".jpg","url":"https://res.cloudinary.com/duqhyfegq/image/upload/v1682272784/small_fotos_corujas_2ce24c5172.jpg","hash":"small_fotos_corujas_2ce24c5172","mime":"image/jpeg","name":"small_fotos-corujas.jpg","path":null,"size":27.81,"width":500,"height":262,"provider_metadata":{"public_id":"small_fotos_corujas_2ce24c5172","resource_type":"image"}},"medium":{"ext":".jpg","url":"https://res.cloudinary.com/duqhyfegq/image/upload/v1682272784/medium_fotos_corujas_2ce24c5172.jpg","hash":"medium_fotos_corujas_2ce24c5172","mime":"image/jpeg","name":"medium_fotos-corujas.jpg","path":null,"size":57.17,"width":750,"height":393,"provider_metadata":{"public_id":"medium_fotos_corujas_2ce24c5172","resource_type":"image"}},"thumbnail":{"ext":".jpg","url":"https://res.cloudinary.com/duqhyfegq/image/upload/v1682272782/thumbnail_fotos_corujas_2ce24c5172.jpg","hash":"thumbnail_fotos_corujas_2ce24c5172","mime":"image/jpeg","name":"thumbnail_fotos-corujas.jpg","path":null,"size":8.19,"width":245,"height":128,"provider_metadata":{"public_id":"thumbnail_fotos_corujas_2ce24c5172","resource_type":"image"}}},"hash":"fotos_corujas_2ce24c5172","ext":".jpg","mime":"image/jpeg","size":109.6,"url":"https://res.cloudinary.com/duqhyfegq/image/upload/v1682272782/fotos_corujas_2ce24c5172.jpg","previewUrl":null,"provider":"cloudinary","provider_metadata":{"public_id":"fotos_corujas_2ce24c5172","resource_type":"image"},"createdAt":"2023-04-23T17:59:44.900Z","updatedAt":"2023-04-23T17:59:44.900Z"}}},"author":{"data":{"id":2,"attributes":{"name":"ghapa","createdAt":"2023-04-08T17:42:17.508Z","updatedAt":"2023-04-15T17:03:57.903Z"}}},"categorie":{"data":{"id":2,"attributes":{"name":"JavaScript","createdAt":"2023-04-08T17:46:11.205Z","updatedAt":"2023-04-10T17:50:07.373Z","publishedAt":"2023-04-08T17:46:19.476Z"}}}}},"content":"<p>Era uma vez uma coruja chamada Aurora. Ela era uma coruja muito tímida e sempre se sentia insegura ao interagir com outros animais da floresta. Mas havia uma coisa que Aurora adorava fazer mais do que qualquer outra coisa: cantar.</p>\n<p>Todas as noites, Aurora cantava suavemente enquanto voava pela floresta. Ela amava a sensação de sua voz flutuando no ar noturno, mas sempre fazia isso quando sabia que não havia ninguém por perto para ouvir. Ela tinha medo de cantar em público e que os outros animais zombassem dela.</p>\n<p>Um dia, Aurora conheceu um filhote de coruja chamado Oliver. Oliver também amava cantar e ouvia Aurora cantando todas as noites. Ele admirava a voz de Aurora e queria aprender a cantar como ela. Aurora ficou surpresa e um pouco envergonhada que alguém tinha ouvido sua voz, mas ficou feliz em saber que alguém gostava da sua música.</p>\n<p>Com o tempo, Aurora começou a cantar para Oliver, e ele adorava ouvir sua voz. Ele a encorajou a cantar mais alto e mais forte. Aurora ainda estava um pouco tímida, mas começou a ganhar confiança com Oliver. Ela percebeu que seu medo de cantar em público era apenas um obstáculo que ela precisava superar.</p>\n<p>Um dia, Oliver perguntou a Aurora por que ela não cantava para outros animais da floresta. Aurora explicou que estava muito tímida e tinha medo do que os outros pensariam. Oliver sorriu e disse a Aurora que sua voz era linda e que ela deveria compartilhar sua música com o mundo.</p>\n<p>Com a ajuda de Oliver, Aurora finalmente encontrou a coragem de cantar em público. Ela se apresentou na árvore principal da floresta e cantou com toda a sua voz. Para sua surpresa, todos os animais pararam para ouvi-la e aplaudiram quando ela terminou. Aurora percebeu que sua música tinha o poder de trazer alegria para os outros, e ela nunca mais teve medo de cantar em público novamente.</p>\n<p>A partir daquele dia, Aurora se tornou uma das corujas mais conhecidas da floresta. As outras corujas vinham pedir conselhos a ela sobre como cantar e, às vezes, ela se juntava a outros animais para tocar música juntos. E assim, a coruja tímida encontrou sua voz e descobriu uma nova confiança dentro de si mesma.</p>\n","categoryName":["JavaScript","Ruby"]},"__N_SSG":true}